{
   "code":201,
   "status":"success",
   "data":{
      "document_id":"ANROMlLx9K3cSEK0j6us",
      "predict_id":"573acdad-b099-4e67-a060-c863966c5ab8",
      "person":{
         "name":"Gabriela Ehlert",
         "analysis":{
            "essay":{
               "analyzed_text":"Thank you guys very much. It's a privilege to be here at this Farm where leaders and business science art diplomacy and world affairs have gathered for many many years to discuss how we can advance Prosperity security and peace. I'm here today to represent the interests of the American people and do a firm America's friendship and partnership in building a better world. Like all nations represented at this great Forum America hopes for a future in which everyone can prosper and every child can grow up free from violence poverty and fear. Over the past year, we have made extraordinary strides in the US. We're lifting up forgotten communities creating exciting New Opportunities and helping every American find their path to the American dream.",
               "word_count":126,
               "detected_language":"en",
               "sentiment_analysis":{
                  "positive":{
                     "result":26.385175704956055
                  },
                  "neutral":{
                     "result":36.15134811401367
                  },
                  "negative":{
                     "result":37.463478088378906
                  }
               },
               "audio_to_text":true,
               "audio_recognition":{
                  "description":"Spectrum API",
                  "url":"https://storage.googleapis.com/nq-audio/prd/power-skills/neuroquest.ai/018bf0b1-a88d-43ba-97f2-7d9b3a80cf95/TRUMP-WEF-2018.wav",
                  "created":"2024-04-07 19:15:01 UTC",
                  "lang":"en",
                  "document_id":"TZwF6aPPHgDDQ7mcfEcy"
               }
            },
            "personalities":[
               {
                  "openness":{
                     "name":"Openness",
                     "acronym":"O",
                     "result":34.40043258666992,
                     "score":"low",
                     "traits":[
                        {
                           "trait":1,
                           "name":"Imagination",
                           "result":59.62384033203125,
                           "score":"high"
                        },
                        {
                           "trait":2,
                           "name":"Artistic Interests",
                           "result":41.412723541259766,
                           "score":"low"
                        },
                        {
                           "trait":3,
                           "name":"Emotionality",
                           "result":39.860408782958984,
                           "score":"low"
                        },
                        {
                           "trait":4,
                           "name":"Adventurousness",
                           "result":34.13905334472656,
                           "score":"low"
                        },
                        {
                           "trait":5,
                           "name":"Intellect",
                           "result":38.56296920776367,
                           "score":"low"
                        },
                        {
                           "trait":6,
                           "name":"Liberalism",
                           "result":6.787606239318848,
                           "score":"low"
                        }
                     ]
                  },
                  "conscientiousness":{
                     "name":"Conscientiousness",
                     "acronym":"C",
                     "result":97.03154004907802,
                     "score":"high",
                     "traits":[
                        {
                           "trait":1,
                           "name":"Self-Efficacy",
                           "result":93.77831268310547,
                           "score":"high"
                        },
                        {
                           "trait":2,
                           "name":"Orderliness",
                           "result":99.07650265926073,
                           "score":"high"
                        },
                        {
                           "trait":3,
                           "name":"Dutifulness",
                           "result":97.99115166770834,
                           "score":"high"
                        },
                        {
                           "trait":4,
                           "name":"Achievement-Striving",
                           "result":95.47309054229622,
                           "score":"high"
                        },
                        {
                           "trait":5,
                           "name":"Self-Discipline",
                           "result":99.84818919822798,
                           "score":"high"
                        },
                        {
                           "trait":6,
                           "name":"Cautiousness",
                           "result":90.51383972167969,
                           "score":"high"
                        }
                     ]
                  },
                  "extraversion":{
                     "name":"Extraversion",
                     "acronym":"E",
                     "result":55.039390563964844,
                     "score":"high",
                     "traits":[
                        {
                           "trait":1,
                           "name":"Friendliness",
                           "result":47.03540802001953,
                           "score":"average"
                        },
                        {
                           "trait":2,
                           "name":"Gregariousness",
                           "result":43.889339447021484,
                           "score":"low"
                        },
                        {
                           "trait":3,
                           "name":"Assertiveness",
                           "result":65.7183609008789,
                           "score":"high"
                        },
                        {
                           "trait":4,
                           "name":"Activity Level",
                           "result":76.78325653076172,
                           "score":"high"
                        },
                        {
                           "trait":5,
                           "name":"Excitement Seeking",
                           "result":31.942277908325195,
                           "score":"low"
                        },
                        {
                           "trait":6,
                           "name":"Cheerfulness",
                           "result":60.13618087768555,
                           "score":"high"
                        }
                     ]
                  },
                  "agreeableness":{
                     "name":"Agreeableness",
                     "acronym":"A",
                     "result":76.80917358398438,
                     "score":"high",
                     "traits":[
                        {
                           "trait":1,
                           "name":"Trust",
                           "result":42.3487434387207,
                           "score":"low"
                        },
                        {
                           "trait":2,
                           "name":"Morality",
                           "result":98.55753005386296,
                           "score":"high"
                        },
                        {
                           "trait":3,
                           "name":"Altruism",
                           "result":71.8472900390625,
                           "score":"high"
                        },
                        {
                           "trait":4,
                           "name":"Cooperation",
                           "result":67.60797882080078,
                           "score":"high"
                        },
                        {
                           "trait":5,
                           "name":"Modesty",
                           "result":56.76189041137695,
                           "score":"high"
                        },
                        {
                           "trait":6,
                           "name":"Sympathy",
                           "result":50.93970489501953,
                           "score":"average"
                        }
                     ]
                  },
                  "neuroticism":{
                     "name":"Neuroticism",
                     "acronym":"N",
                     "result":30.312517166137695,
                     "score":"low",
                     "traits":[
                        {
                           "trait":1,
                           "name":"Anxiety",
                           "result":57.81972122192383,
                           "score":"high"
                        },
                        {
                           "trait":2,
                           "name":"Anger",
                           "result":32.59678649902344,
                           "score":"low"
                        },
                        {
                           "trait":3,
                           "name":"Depression",
                           "result":26.68712615966797,
                           "score":"low"
                        },
                        {
                           "trait":4,
                           "name":"Self-Consciousness",
                           "result":36.74938201904297,
                           "score":"low"
                        },
                        {
                           "trait":5,
                           "name":"Immoderation",
                           "result":22.43869400024414,
                           "score":"low"
                        },
                        {
                           "trait":6,
                           "name":"Vulnerability",
                           "result":32.687782287597656,
                           "score":"low"
                        }
                     ]
                  }
               }
            ],
            "warnings":[
               "For a more accurate analysis, it is better for the text to contain more words than 126."
            ],
            "metrics":[
               {
                  "WEF2023":[
                     {
                        "trait":1,
                        "name":"Analytical Think",
                        "metric":"WEF2023",
                        "result":86.57112749237672,
                        "score":"high"
                     },
                     {
                        "trait":2,
                        "name":"Creative Thinking",
                        "metric":"WEF2023",
                        "result":49.778579394316345,
                        "score":"average"
                     },
                     {
                        "trait":3,
                        "name":"Curiosity and Lifelong Learning",
                        "metric":"WEF2023",
                        "result":49.997651340291185,
                        "score":"average"
                     },
                     {
                        "trait":4,
                        "name":"Leadership and Social Influence",
                        "metric":"WEF2023",
                        "result":55.25874103482377,
                        "score":"high"
                     },
                     {
                        "trait":5,
                        "name":"Empaty and Active Listening",
                        "metric":"WEF2023",
                        "result":44.725121339162186,
                        "score":"low"
                     },
                     {
                        "trait":6,
                        "name":"Technical Literacy",
                        "metric":"WEF2023",
                        "result":62.44859190538045,
                        "score":"high"
                     },
                     {
                        "trait":7,
                        "name":"Quality Control",
                        "metric":"WEF2023",
                        "result":66.32267776824116,
                        "score":"high"
                     },
                     {
                        "trait":8,
                        "name":"Motivation and Self-awareness",
                        "metric":"WEF2023",
                        "result":64.34680760701497,
                        "score":"high"
                     },
                     {
                        "trait":9,
                        "name":"Dependability and Attention to Detail",
                        "metric":"WEF2023",
                        "result":72.63282143576966,
                        "score":"high"
                     },
                     {
                        "trait":10,
                        "name":"Resilence, Flexibility and Agility",
                        "metric":"WEF2023",
                        "result":55.220282466403006,
                        "score":"high"
                     }
                  ]
               },
               {
                  "ORVIS":[
                     {
                        "trait":1,
                        "name":"Leadership",
                        "metric":"ORVIS",
                        "result":44.84744717524603,
                        "score":"low"
                     },
                     {
                        "trait":2,
                        "name":"Organization",
                        "metric":"ORVIS",
                        "result":97.13883706728883,
                        "score":"high"
                     },
                     {
                        "trait":3,
                        "name":"Altruism",
                        "metric":"ORVIS",
                        "result":53.780883008507566,
                        "score":"average"
                     },
                     {
                        "trait":4,
                        "name":"Creativity",
                        "metric":"ORVIS",
                        "result":43.51890076531305,
                        "score":"low"
                     },
                     {
                        "trait":5,
                        "name":"Analysis",
                        "metric":"ORVIS",
                        "result":46.098338452540645,
                        "score":"average"
                     },
                     {
                        "trait":6,
                        "name":"Adventure",
                        "metric":"ORVIS",
                        "result":32.15374837602888,
                        "score":"low"
                     },
                     {
                        "trait":7,
                        "name":"Production",
                        "metric":"ORVIS",
                        "result":80.09111962255622,
                        "score":"high"
                     },
                     {
                        "trait":8,
                        "name":"Erudition",
                        "metric":"ORVIS",
                        "result":45.85622732979911,
                        "score":"average"
                     }
                  ]
               },
               {
                  "OECD":[
                     {
                        "trait":1,
                        "name":"Task Performance",
                        "metric":"OECD",
                        "result":96.73212110500228,
                        "score":"high"
                     },
                     {
                        "trait":2,
                        "name":"Emotional Regulation",
                        "metric":"OECD",
                        "result":36.74938201904297,
                        "score":"low"
                     },
                     {
                        "trait":3,
                        "name":"Collaboration",
                        "metric":"OECD",
                        "result":50.93970489501953,
                        "score":"average"
                     },
                     {
                        "trait":4,
                        "name":"Open-Mindedness",
                        "metric":"OECD",
                        "result":41.412723541259766,
                        "score":"low"
                     },
                     {
                        "trait":5,
                        "name":"Engagement with others",
                        "metric":"OECD",
                        "result":65.7183609008789,
                        "score":"high"
                     }
                  ]
               },
               {
                  "PNQ1":[
                     {
                        "trait":1,
                        "name":"Adventurous",
                        "metric":"PNQ1",
                        "result":31.007449340820312,
                        "score":"low"
                     },
                     {
                        "trait":2,
                        "name":"Pragmatic",
                        "metric":"PNQ1",
                        "result":97.26590128438554,
                        "score":"high"
                     },
                     {
                        "trait":3,
                        "name":"Strategist",
                        "metric":"PNQ1",
                        "result":58.73414702492936,
                        "score":"high"
                     },
                     {
                        "trait":4,
                        "name":"Visionary",
                        "metric":"PNQ1",
                        "result":63.69832356770833,
                        "score":"high"
                     },
                     {
                        "trait":5,
                        "name":"Criative",
                        "metric":"PNQ1",
                        "result":53.55346806844075,
                        "score":"average"
                     }
                  ]
               }
            ]
         }
      },
      "owner":{
         "user_id":"MJumNgU0iud90UsEtohNeh6g0ju1",
         "email":"ederbsd@gmail.com"
      },
      "provider":{
         "name":"NeuroQuest AI",
         "product":"Power-Skills",
         "api":{
            "version":"v1.0.0"
         },
         "model":{
            "name":"Geni",
            "theory":"Multiple Psycholinguistic Features",
            "version":"v1.0.0"
         },
         "date":"2024-04-07 21:21:59 UTC"
      }
   }
}