{"code": 201, "status": "success", "data": {"document_id": "kgQW0XMHHugy4icY58Ii", "predict_id": "c1ee14d6-5e36-4031-a732-57f74c767b7d", "person": {"name": "Justin Schultz", "analysis": {"essay": {"analyzed_text": "o brasil adota o sistema tripartite de poder (legislativo, executivo e judiciário), cuja concepção se baseou na obra “o espírito das leis”( ) de montesquieu. esse sistema nada mais é que a divisão de atribuições dentro de um estado, no qual cada poder terá suas funções típicas e, em alguns casos, atípicas. cabe salientar que essa divisão ocorrerá em todos os entes federativos – união, estados, distrito federal e municípios (os quais não têm poder judiciário). tendo por base a união, indaga-se: quais as principais funções desses poderes. quanto ao poder legislativo, ele é formado pelo congresso nacional, que se compõe da câmara dos deputados (representantes do povo) e do senado federal (representantes dos estados/distrito federal). sua função principal é editar leis e, atipicamente, administrar (organização interna) e julgar. por isso, é fundamental que o povo escolha seus representantes com consciência, evitando a eleição de pessoas de má índole, como as que participaram do mensalão (esquema criminoso em que vários parlamentares receberam propina para votarem segundo as orientações do governo). já o poder executivo é exercido pelo presidente da república com o auxílio dos ministros de estado. sua função precípua é resolver os problemas concretos e individualizados, de acordo com as leis, ou seja, administrar a “máquina estatal”. como funções anômalas, ele pode legislar (medidas provisórias) e julgar. assim como no caso do legislativo, é preciso que o povo analise os candidatos com paciência, e que vote no mais preparado, evitando colocar no comando do país alguém como o ex-presidente fernando collor (governo marcado por corrupções e ilegalidades). por fim, tem-se o poder judiciário (formado pelos tribunais e juízes), o qual possui como órgão máximo o supremo tribunal federal (que se compõe de 11 ministros). sua função típica é julgar, aplicando as leis aos casos concretos a fim de dirimir os conflitos de interesse; já atipicamente, ele pode legislar (súmulas vinculantes) e administrar. é fundamental que esses julgamentos sejam imparciais e ponderados, evitando, assim, o cometimento de injustiças. diante de todas essas explanações, fica evidente que tal divisão de poderes é a mais adequada ao brasil, pois cada um deles é obrigado a realizar suas funções segundo as leis. a partir do momento ( ) que há abuso de poder por parte de quaisquer dos poderes, os outros poderão intervir para coibir o excesso; esse controle é denominado de “freios e contrapesos”. enfim, se com o sistema tripartite de poder há tanta corrupção, desvios de verbas públicas, abusos, etc., caso essas funções pertencessem a um único poder (como nas monarquias)( ) o caos reinaria no país; por isso, reafirma-se: o voto consciente é a solução para que o estado seja bem gerido pelos três poderes que o constitui.", "word_count": 448, "detected_language": "pt-br"}, "personalities": [{"openness": {"trait_id": "big5_openness", "name": "Abertura à Experiência", "acronym": "O", "raw_score": 68.4153570186666, "percentile": 70.43072814694538, "confidence": 98.10646217307529, "traits": [{"trait": 1, "trait_id": "facet_imagination", "name": "Imaginação", "raw_score": 70.20272733292101, "percentile": 76.4116385011505, "confidence": 98.14058269186103}, {"trait": 2, "trait_id": "facet_artistic_interests", "name": "Interesses Artísticos", "raw_score": 65.01977707458288, "percentile": 67.69180043271733, "confidence": 98.00284695349805}, {"trait": 3, "trait_id": "facet_emotionality", "name": "Emotividade", "raw_score": 70.98384169581396, "percentile": 69.78776795607108, "confidence": 98.18820473960373}, {"trait": 4, "trait_id": "facet_adventurousness", "name": "Desejo de Aventura", "raw_score": 65.33013009222302, "percentile": 67.54567388223535, "confidence": 97.98273051057504}, {"trait": 5, "trait_id": "facet_intellect", "name": "Intelectualidade", "raw_score": 69.72889112672087, "percentile": 70.50319560737645, "confidence": 98.16958334719604}, {"trait": 6, "trait_id": "facet_liberalism", "name": "Liberalismo", "raw_score": 69.22677478973783, "percentile": 70.64429250212156, "confidence": 98.15482479571793}]}}, {"conscientiousness": {"trait_id": "big5_conscientiousness", "name": "Conscienciosidade", "acronym": "C", "raw_score": 70.7010796126459, "percentile": 76.6928647604213, "confidence": 98.0746441458205, "traits": [{"trait": 1, "trait_id": "facet_self_efficacy", "name": "Auto-Eficácia", "raw_score": 73.11170877054452, "percentile": 75.62041478757513, "confidence": 98.12539973439421}, {"trait": 2, "trait_id": "facet_orderliness", "name": "Organização", "raw_score": 66.45339618027201, "percentile": 74.19474316464384, "confidence": 98.02196351749109}, {"trait": 3, "trait_id": "facet_dutifulness", "name": "Responsabilidade", "raw_score": 67.26122424603962, "percentile": 72.25260167761961, "confidence": 97.98189629719347}, {"trait": 4, "trait_id": "facet_achievement_striving", "name": "Determinação", "raw_score": 72.59332761745969, "percentile": 76.9982625165529, "confidence": 98.10350999297408}, {"trait": 5, "trait_id": "facet_self_discipline", "name": "Auto-Disciplina", "raw_score": 73.51771587136251, "percentile": 82.58472397713014, "confidence": 98.1260059294458}, {"trait": 6, "trait_id": "facet_cautiousness", "name": "Cautela", "raw_score": 71.26910499019705, "percentile": 78.50644243900624, "confidence": 98.08908940342428}]}}, {"extraversion": {"trait_id": "big5_extraversion", "name": "Extroversão", "acronym": "E", "raw_score": 45.467291497358765, "percentile": 47.31805373979873, "confidence": 97.46934664201483, "traits": [{"trait": 1, "trait_id": "facet_friendliness", "name": "Simpatia", "raw_score": 48.10437372508366, "percentile": 54.496385729448185, "confidence": 97.62236068494352}, {"trait": 2, "trait_id": "facet_gregariousness", "name": "Sociabilidade", "raw_score": 49.965071594650816, "percentile": 53.286943099159906, "confidence": 97.6961693056252}, {"trait": 3, "trait_id": "facet_assertiveness", "name": "Assertividade", "raw_score": 42.450327990452145, "percentile": 44.00922389361345, "confidence": 97.28991745236262}, {"trait": 4, "trait_id": "facet_activity_level", "name": "Nível de Atividade", "raw_score": 41.906125711089345, "percentile": 44.44198108424477, "confidence": 97.28172346412701}, {"trait": 5, "trait_id": "facet_excitement_seeking", "name": "Busca de Excitação", "raw_score": 45.60373159042638, "percentile": 34.792136836547435, "confidence": 97.47216437498354}, {"trait": 6, "trait_id": "facet_cheerfulness", "name": "Bom Humor", "raw_score": 44.774118372450275, "percentile": 52.88165179577861, "confidence": 97.45374457004702}]}}, {"agreeableness": {"trait_id": "big5_agreeableness", "name": "Amabilidade", "acronym": "A", "raw_score": 52.03952871557508, "percentile": 54.21369615732369, "confidence": 97.70459498433765, "traits": [{"trait": 1, "trait_id": "facet_trust", "name": "Confiança", "raw_score": 55.67262515088255, "percentile": 60.87612368935171, "confidence": 97.83218286153304}, {"trait": 2, "trait_id": "facet_morality", "name": "Moralidade", "raw_score": 48.79087368341165, "percentile": 52.002745125017164, "confidence": 97.55222642550117}, {"trait": 3, "trait_id": "facet_altruism", "name": "Altruísmo", "raw_score": 52.66017621412489, "percentile": 56.340568948755084, "confidence": 97.74513497207079}, {"trait": 4, "trait_id": "facet_cooperation", "name": "Cooperação", "raw_score": 51.58845249388013, "percentile": 57.21146959038421, "confidence": 97.71297462804212}, {"trait": 5, "trait_id": "facet_modesty", "name": "Modéstia", "raw_score": 52.15514802813311, "percentile": 46.78873569570085, "confidence": 97.71961196845174}, {"trait": 6, "trait_id": "facet_sympathy", "name": "Empatia", "raw_score": 51.369896723018115, "percentile": 52.06253389473312, "confidence": 97.66543905042701}]}}, {"neuroticism": {"trait_id": "big5_neuroticism", "name": "Estabilidade Emocional", "acronym": "N", "raw_score": 23.564119767128876, "percentile": 17.24347170879026, "confidence": 87.84472970914692, "traits": [{"trait": 1, "trait_id": "facet_anxiety", "name": "Ansiedade", "raw_score": 22.48522151222419, "percentile": 19.513584652946196, "confidence": 91.975926678801}, {"trait": 2, "trait_id": "facet_anger", "name": "Raiva", "raw_score": 29.608012453643244, "percentile": 20.461119332843655, "confidence": 83.29517672796386}, {"trait": 3, "trait_id": "facet_depression", "name": "Melancolia", "raw_score": 19.527717067331302, "percentile": 7.369357685370661, "confidence": 93.01510825999786}, {"trait": 4, "trait_id": "facet_self_consciousness", "name": "Auto-Consciência", "raw_score": 20.525167166681268, "percentile": 16.365790469474753, "confidence": 94.06778609133568}, {"trait": 5, "trait_id": "facet_immoderation", "name": "Impulsividade", "raw_score": 21.917094860820526, "percentile": 14.524791963973072, "confidence": 81.71980642538243}, {"trait": 6, "trait_id": "facet_vulnerability", "name": "Suscetível ao Stress", "raw_score": 27.321505542072742, "percentile": 25.22618614813322, "confidence": 82.9945740714007}]}}], "warnings": ["For a more accurate analysis, it is better for the text to contain more words than 448."]}}, "information": {"processed_by": "srv-1", "processing_time": 5.5901754770000025}, "owner": "e@neuroquest.ai", "provider": {"name": "NeuroQuest AI", "product": "Persona-Predict", "api": {"name": "Ada", "description": "Multiple Psycholinguistic Features", "version": "v2.0.0"}, "model": {"name": "Claudia", "theory": "Big 5 Personality Traits", "version": "v2.0.0"}, "date": "2025-01-01 20:13:29 UTC"}}}